{"NqCyO4cAKh7PcZf0/pL8eg==":"mbr-1920x1280.jpg","FQoD5LPCiT3/H3F92HT0ug==":"%E5%BE%AE%E4%BF%A1%E5%9B%BE%E7%89%87-20210714182908-2000x1068.jpg","jkbxlMyYRx5BLzwBbXllMg==":"%E5%BE%AE%E4%BF%A1%E5%9B%BE%E7%89%87-20210714182908-2000x1068.jpeg","NtSaXp9wJ3FJ75nRfFjFOQ==":"%E5%BE%AE%E4%BF%A1%E5%9B%BE%E7%89%87-20210714182908-2000x1068.jpeg","HWTgbd3dEzD45Q7Ck+JWOA==":"%E5%BE%AE%E4%BF%A1%E5%9B%BE%E7%89%87-20210714200641-96x96.jpg","JR/ZFB9xWB3XouVBmpfvjw==":"u=403049202,4141547040&fm=26&fmt=auto&gp=0.webp","7FQAo1C2+cC9oqzO2mIavA==":"src=http___img3.duitang.com_uploads_item_201504_29_20150429102045_vxarn.jpeg&refer=http___img3.duitang-506x759.jpeg","dbpIaiayVtDJBW4MyxYETg==":"%E5%AE%9A%E6%80%A7%E7%A0%94%E7%A9%B6.webp","8fiyq1XR/YavZXDuAiyQxQ==":"u=403049202,4141547040&fm=26&fmt=auto&gp=0-1.webp","48uPXEKfMRqQ1sHfNt27Pg==":"src=http___img3.duitang.com_uploads_item_201504_29_20150429102045_vxarn.jpeg&refer=http___img3.duitang-1-506x759.jpeg","vB3sZpuTUOHHvX4HZrGHEg==":"%E5%AE%9A%E6%80%A7%E7%A0%94%E7%A9%B6.webp","ovCP2t/2cIRGqyy0vganAQ==":"%E8%89%BA%E6%9C%AF%E5%8F%B2%E5%AF%BC%E8%AE%BA.webp","VcthS0RZ/Tj9e1Zb/YHJWg==":"%E8%A7%86%E8%A7%89%E8%AE%BE%E8%AE%A1.webp","8qPEGCiwAOA3ynMVcGys7w==":"%E7%94%B5%E5%BD%B1%E9%85%8D%E4%B9%90.webp","EzA9ok+OBG8tltJ4rI2+Xg==":"%E7%94%B5%E5%BD%B1%E9%85%8D%E4%B9%90.webp","FScSkhQ3BUh+8TRDo7BXIQ==":"%E5%AE%9A%E6%80%A7%E7%A0%94%E7%A9%B6.webp"}